kk/core/__init__.py
kk/core/core.py
kk/core/main.py
kk/core/plugin_utils.py
kk_core-0.1.0.dist-info/entry_points.txt
kk_core-0.1.0.dist-info/WHEEL
kk_core-0.1.0.dist-info/METADATA
kk_core-0.1.0.dist-info/RECORD
