Metadata-Version: 2.1
Name: kk-core
Version: 0.1.0
Summary: 
Author: Uriel Mandujano
Author-email: uriel.mandujano14@gmail.com
Requires-Python: >=3.9,<4.0
Classifier: Programming Language :: Python :: 3
Classifier: Programming Language :: Python :: 3.9
Requires-Dist: typer (>=0.3.2,<0.4.0)
